cjm_transcription_plugin_voxtral_hf/__init__.py
cjm_transcription_plugin_voxtral_hf/_modidx.py
cjm_transcription_plugin_voxtral_hf/meta.py
cjm_transcription_plugin_voxtral_hf/plugin.py
cjm_transcription_plugin_voxtral_hf-0.0.16.dist-info/licenses/LICENSE
cjm_transcription_plugin_voxtral_hf-0.0.16.dist-info/METADATA
cjm_transcription_plugin_voxtral_hf-0.0.16.dist-info/WHEEL
cjm_transcription_plugin_voxtral_hf-0.0.16.dist-info/entry_points.txt
cjm_transcription_plugin_voxtral_hf-0.0.16.dist-info/top_level.txt
cjm_transcription_plugin_voxtral_hf-0.0.16.dist-info/RECORD
